orbis_plugin_aggregation_spotlight/__init__.py
orbis_plugin_aggregation_spotlight/main.py
orbis_plugin_aggregation_spotlight-2.3.0.dist-info/LICENSE
orbis_plugin_aggregation_spotlight-2.3.0.dist-info/METADATA
orbis_plugin_aggregation_spotlight-2.3.0.dist-info/WHEEL
orbis_plugin_aggregation_spotlight-2.3.0.dist-info/top_level.txt
orbis_plugin_aggregation_spotlight-2.3.0.dist-info/RECORD
