Metadata-Version: 2.1
Name: orbis-plugin-aggregation-spotlight
Version: 2.3.0
Summary: The spotlight aggregation plugin for Orbis
Home-page: https://github.com/orbis-eval/orbis_plugin_aggregation_spotlight
Author: fabod
License: GPL2
Platform: UNKNOWN
Requires-Python: >3.6
Requires-Dist: pyspotlight
